Workbook

Sheet Sheet1
A1: Employee ID | B1: Name | C1: Department | D1: Salary | E1: Joining Date
A2: E101 | B2: Amit Sharma | C2: HR | D2: 32000 | E2: 12-01-2022
A3: E102 | B3: Neha Verma | C3: IT | D3: 45000 | E3: 05-03-2021
A4: E103 | B4: Rahul Mehta | C4: Finance | D4: 38000 | E4: 18-07-2020
A5: E104 | B5: Pooja Singh | C5: IT | D5: 52000 | E5: 10-11-2019
A6: E105 | B6: Ankit Patel | C6: Sales | D6: 30000 | E6: 25-06-2023
A7: E106 | B7: Amit Sharma | C7: HR | D7: =RANDBETWEEN(25000,65000) -> 50416 | E7: 12-01-2023
A8: E107 | B8: Neha Verma | C8: IT | D8: =RANDBETWEEN(25000,65000) -> 44581 | E8: 05-03-2022
A9: E108 | B9: Rahul Mehta | C9: Finance | D9: =RANDBETWEEN(25000,65000) -> 37698 | E9: 18-07-2021
A10: E109 | B10: Pooja Singh | C10: IT | D10: =RANDBETWEEN(25000,65000) -> 44735 | E10: 10-11-2020
A11: E110 | B11: Ankit Patel | C11: Sales | D11: =RANDBETWEEN(25000,65000) -> 57862 | E11: 25-06-2024
A12: E111 | B12: Amit Sharma | C12: HR | D12: =RANDBETWEEN(25000,65000) -> 29338 | E12: 12-01-2024
A13: E112 | B13: Neha Verma | C13: IT | D13: =RANDBETWEEN(25000,65000) -> 44924 | E13: 05-03-2023
A14: E113 | B14: Rahul Mehta | C14: Finance | D14: =RANDBETWEEN(25000,65000) -> 51682 | E14: 18-07-2022
A15: E114 | B15: Pooja Singh | C15: IT | D15: =RANDBETWEEN(25000,65000) -> 49401 | E15: 10-11-2021
A16: E115 | B16: Ankit Patel | C16: Sales | D16: =RANDBETWEEN(25000,65000) -> 54820 | E16: 25-06-2025
A17: E116 | B17: Amit Sharma | C17: HR | D17: =RANDBETWEEN(25000,65000) -> 42407 | E17: 12-01-2025
A18: E117 | B18: Neha Verma | C18: IT | D18: =RANDBETWEEN(25000,65000) -> 44900 | E18: 05-03-2024
... A21: E120 | B21: Ankit Patel | C21: Sales | D21: =RANDBETWEEN(25000,65000) -> 51526 | E21: 25-06-2026

Sheet Sheet2
A1: Monthly Sales Report
A2: Product Name | B2: Region | C2: Sales Amount | D2: Salesperson
A3: Laptop Dell Inspiron 15 | B3: North | C3: 45000 | D3: Ramesh
A4: HP Wireless Mouse | B4: West | C4: 1200 | D4: Sneha
A5: Samsung 24-inch Monitor | B5: East | C5: 18000 | D5: Arjun
A6: Lenovo ThinkPad E14 Laptop | B6: South | C6: 62000 | D6: Kavita
A7: Laptop Dell Inspiron 16 | B7: North | C7: 9113 | D7: Ramesh
A8: HP Wireless Mouse | B8: West | C8: 2071 | D8: Sneha
A9: Samsung 24-inch Monitor | B9: East | C9: 2683 | D9: Arjun
A10: Lenovo ThinkPad E14 Laptop | B10: South | C10: 2221 | D10: Kavita
A11: Laptop Dell Inspiron 17 | B11: North | C11: 7764 | D11: Ramesh
A12: HP Wireless Mouse | B12: West | C12: 3657 | D12: Sneha
A13: Samsung 24-inch Monitor | B13: East | C13: 9261 | D13: Arjun
A14: Lenovo ThinkPad E14 Laptop | B14: South | C14: 2721 | D14: Kavita
... A22: Lenovo ThinkPad E14 Laptop | B22: South | C22: 6629 | D22: Kavita

Sheet Sheet3
A1: Roll No | B1: Student Name | C1: Maths | D1: Science | E1: English | F1: Percentage | J1: Employee Name | K1: Department | L1: Salary
A2: 1 | B2: Aakash | C2: 78 | D2: 82 | E2: 74 | F2: =((C2+D2+E2)/300)*100 -> 78 | J2: Suresh | K2: HR | L2: 28000
A3: 2 | B3: Bhavya | C3: 65 | D3: 70 | E3: 68 | F3: =((C3+D3+E3)/300)*100 -> 67.666667 | J3: Meena | K3: IT | L3: 45000
A4: 3 | B4: Chirag | C4: 90 | D4: 88 | E4: 92 | F4: =((C4+D4+E4)/300)*100 -> 90 | J4: Karan | K4: IT | L4: 50000 | O4: Suresh | P4: HR | Q4: 28000
A5: 4 | B5: Divya | C5: 35 | D5: 40 | E5: 38 | F5: =((C5+D5+E5)/300)*100 -> 37.666667 | J5: Ritu | K5: Finance | L5: 42000 | O5: Aman | P5: HR | Q5: 30000 | S5: Meena | T5: IT | U5: 45000
A6: 5 | B6: Esha | C6: 55 | D6: 60 | E6: 58 | F6: =((C6+D6+E6)/300)*100 -> 57.666667 | J6: Aman | K6: HR | L6: 30000 | O6: Suresh | P6: HR | Q6: 54524 | S6: Karan | T6: IT | U6: 50000
A7: 6 | B7: Aakash | C7: 36 | D7: 36 | E7: 27 | F7: =((C7+D7+E7)/300)*100 -> 33 | J7: Neel | K7: Finance | L7: 38000 | O7: Aman | P7: HR | Q7: 47614 | S7: Meena | T7: IT | U7: 59613
A8: 7 | B8: Bhavya | C8: 51 | D8: 43 | E8: 47 | F8: =((C8+D8+E8)/300)*100 -> 47 | J8: Suresh | K8: HR | L8: 54524 | O8: Suresh | P8: HR | Q8: 56063 | S8: Karan | T8: IT | U8: 49390
A9: 8 | B9: Chirag | C9: 92 | D9: 70 | E9: 96 | F9: =((C9+D9+E9)/300)*100 -> 86 | J9: Meena | K9: IT | L9: 59613 | O9: Aman | P9: HR | Q9: 47483 | S9: Meena | T9: IT | U9: 31298
A10: 9 | B10: Divya | C10: 28 | D10: 94 | E10: 41 | F10: =((C10+D10+E10)/300)*100 -> 54.333333 | J10: Karan | K10: IT | L10: 49390 | O10: Suresh | P10: HR | Q10: 54377 | S10: Karan | T10: IT | U10: 45248
A11: 10 | B11: Esha | C11: 76 | D11: 36 | E11: 49 | F11: =((C11+D11+E11)/300)*100 -> 53.666667 | J11: Ritu | K11: Finance | L11: 61548 | Q11: =SUM(Q4:Q10) -> 318061 | S11: Meena | T11: IT | U11: 56005
A12: 11 | B12: Aakash | C12: 70 | D12: 79 | E12: 46 | F12: =((C12+D12+E12)/300)*100 -> 65 | J12: Aman | K12: HR | L12: 47614 | U12: =sum(U5:U11)
A13: 12 | B13: Bhavya | C13: 79 | D13: 78 | E13: 33 | F13: =((C13+D13+E13)/300)*100 -> 63.333333 | J13: Neel | K13: Finance | L13: 48476
A14: 13 | B14: Chirag | C14: 81 | D14: 30 | E14: 70 | F14: =((C14+D14+E14)/300)*100 -> 60.333333 | J14: Suresh | K14: HR | L14: 56063
A15: 14 | B15: Divya | C15: 73 | D15: 79 | E15: 69 | F15: =((C15+D15+E15)/300)*100 -> 73.666667 | J15: Meena | K15: IT | L15: 31298
A16: 15 | B16: Esha | C16: 46 | D16: 40 | E16: 84 | F16: =((C16+D16+E16)/300)*100 -> 56.666667 | J16: Karan | K16: IT | L16: 45248
A17: 16 | B17: Aakash | C17: 48 | D17: 64 | E17: 90 | F17: =((C17+D17+E17)/300)*100 -> 67.333333 | J17: Ritu | K17: Finance | L17: 47986
A18: 17 | B18: Bhavya | C18: 91 | D18: 85 | E18: 94 | F18: =((C18+D18+E18)/300)*100 -> 90 | J18: Aman | K18: HR | L18: 47483
A19: 18 | B19: Chirag | C19: 79 | D19: 77 | E19: 85 | F19: =((C19+D19+E19)/300)*100 -> 80.333333 | J19: Neel | K19: Finance | L19: 59819
A20: 19 | B20: Divya | C20: 50 | D20: 64 | E20: 93 | F20: =((C20+D20+E20)/300)*100 -> 69 | J20: Suresh | K20: HR | L20: 54377
A21: 20 | B21: Esha | C21: 46 | D21: 47 | E21: 49 | F21: =((C21+D21+E21)/300)*100 -> 47.333333 | J21: Meena | K21: IT | L21: 56005

Sheet Sheet4
A1: Employee Name | B1: Salary | F1: Roll No | G1: Name | H1: Marks | J1: Product | K1: Sales Amount | M1: Order ID | N1: Sales Amount
A2: Rohit | B2: 28000 | F2: 1 | G2: Aman | H2: 85 | J2: Mobile | K2: 22000 | M2: O101 | N2: 4500
A3: Simran | B3: 34000 | F3: 2 | G3: Bharti | H3: 72 | J3: Headphones | K3: 3500 | M3: O102 | N3: 12000
A4: Vijay | B4: 51000 | F4: 3 | G4: Chetan | H4: 39 | J4: Laptop | K4: 58000 | M4: O103 | N4: 8000 | P4: count(greater than 10000 | Q4: =COUNTIF(N2:N21,">10000") -> 12
A5: Nisha | B5: 47000 | F5: 4 | G5: Deepa | H5: 91 | J5: Keyboard | K5: 1800 | M5: O104 | N5: 25000 | P5: count(below 5000) | Q5: =COUNTIF(N2:N21,"<5000") -> 4
A6: Mohan | B6: 29000 | F6: 5 | G6: Farhan | H6: 28 | J6: Tablet | K6: 12000 | M6: O105 | N6: 3000
A7: Rohit | B7: 45865 | F7: 6 | G7: Aman | H7: 49 | J7: Mobile | K7: 23207 | M7: O106 | N7: 15000
A8: Simran | B8: 36771 | F8: 7 | G8: Bharti | H8: 98 | J8: Headphones | K8: 17517 | M8: O107 | N8: 5108
A9: Vijay | B9: 56595 | F9: 8 | G9: Chetan | H9: 95 | J9: Laptop | K9: 17035 | M9: O108 | N9: 19570
A10: Nisha | B10: 52197 | F10: 9 | G10: Deepa | H10: 52 | J10: Keyboard | K10: 5483 | M10: O109 | N10: 18434
A11: Mohan | B11: 70017 | F11: 10 | G11: Farhan | H11: 98 | J11: Tablet | K11: 18618 | M11: O110 | N11: 18856
A12: Rohit | B12: 52312 | F12: 11 | G12: Aman | H12: 30 | J12: Mobile | K12: 9383 | M12: O111 | N12: 7888
A13: Simran | B13: 57270 | F13: 12 | G13: Bharti | H13: 91 | J13: Headphones | K13: 17991 | M13: O112 | N13: 3624
A14: Vijay | B14: 50225 | F14: 13 | G14: Chetan | H14: 90 | J14: Laptop | K14: 18461 | M14: O113 | N14: 6151
A15: Nisha | B15: 27010 | F15: 14 | G15: Deepa | H15: 92 | J15: Keyboard | K15: 28291 | M15: O114 | N15: 3993
A16: Mohan | B16: 65135 | F16: 15 | G16: Farhan | H16: 73 | J16: Tablet | K16: 11103 | M16: O115 | N16: 16739
A17: Rohit | B17: 26810 | F17: 16 | G17: Aman | H17: 86 | J17: Mobile | K17: 3798 | M17: O116 | N17: 17653
... A21: Mohan | B21: 28840 | F21: 20 | G21: Farhan | H21: 88 | J21: Tablet | K21: 19965 | M21: O120 | N21: 13880

Sheet Sheet5
A1: Roll No | B1: Student Name | C1: Marks | D1: Result | G1: Employee Name | H1: Salary | I1: Bonus Status | K1: Student Name | L1: Marks | M1: Grade | P1: Name | Q1: Age | R1: Experience (Years) | S1: Eligible
A2: 1 | B2: Aman | C2: 78 | D2: =IF(Sheet5!C2>=40,"PASS","FAIL") -> PASS | G2: Rohit | H2: 28000 | I2: =IF(H2>=40000,"BONUS","NO BONUS") -> NO BONUS | K2: Aman | L2: 82 | M2: =IF(L2>=75,"A",IF(L2>=60,"B",IF(L2>=40,"C","FAIL"))) -> A | P2: Rohit | Q2: 25 | R2: 2 | S2: =IF(AND(Q2>=21,R2>=1),"ELIGIBLE","NOT ELIGIBLE") -> ELIGIBLE
A3: 2 | B3: Bharti | C3: 35 | D3: =IF(Sheet5!C3>=40,"PASS","FAIL") -> FAIL | G3: Simran | H3: 45000 | I3: =IF(H3>=40000,"BONUS","NO BONUS") -> BONUS | K3: Bharti | L3: 67 | M3: =IF(L3>=75,"A",IF(L3>=60,"B",IF(L3>=40,"C","FAIL"))) -> B | P3: Simran | Q3: 20 | R3: 1 | S3: =IF(AND(Q3>=21,R3>=1),"ELIGIBLE","NOT ELIGIBLE") -> NOT ELIGIBLE
A4: 3 | B4: Rohan | C4: 62 | D4: =IF(Sheet5!C4>=40,"PASS","FAIL") -> PASS | G4: Vijay | H4: 52000 | I4: =IF(H4>=40000,"BONUS","NO BONUS") -> BONUS | K4: Rohan | L4: 45 | M4: =IF(L4>=75,"A",IF(L4>=60,"B",IF(L4>=40,"C","FAIL"))) -> C | P4: Vijay | Q4: 30 | R4: 5 | S4: =IF(AND(Q4>=21,R4>=1),"ELIGIBLE","NOT ELIGIBLE") -> ELIGIBLE
A5: 4 | B5: Deepa | C5: 40 | D5: =IF(Sheet5!C5>=40,"PASS","FAIL") -> PASS | G5: Nisha | H5: 30000 | I5: =IF(H5>=40000,"BONUS","NO BONUS") -> NO BONUS | K5: Deepa | L5: 33 | M5: =IF(L5>=75,"A",IF(L5>=60,"B",IF(L5>=40,"C","FAIL"))) -> FAIL | P5: Nisha | Q5: 22 | R5: 0 | S5: =IF(AND(Q5>=21,R5>=1),"ELIGIBLE","NOT ELIGIBLE") -> NOT ELIGIBLE
A6: 5 | B6: Farhan | C6: 28 | D6: =IF(Sheet5!C6>=40,"PASS","FAIL") -> FAIL | K6: Farhan | L6: 90 | M6: =IF(L6>=75,"A",IF(L6>=60,"B",IF(L6>=40,"C","FAIL"))) -> A
C10: Student Name | D10: Attendance % | E10: Assignment Submitted | F10: Eligible | I10: Customer Name | J10: Purchase Amount | K10: Membership | L10: Discount | O10: Applicant | P10: Salary | Q10: CIBIL Score | R10: Loan Status
C11: Aman | D11: 85 | E11: Yes | F11: {=IF(AND(D11>=75,E11=YES), "ELIGIBLE", "NOT ELIGIBLE")} -> #NAME? | I11: Aakash | J11: 9000 | K11: No | L11: =IF(OR(J11>=10000, K11="Yes"), "Yes", "No") -> No | O11: Rohit | P11: 35000 | Q11: 720 | R11: =IF(OR(P11>=40000, Q11="700"), "APPROVED", "No") -> No
C12: Bharti | D12: 72 | E12: Yes | I12: Bhavna | J12: 12000 | K12: No | L12: =IF(OR(J12>=10000, K12="Yes"), "Yes", "No") -> Yes | O12: Simran | P12: 25000 | Q12: 680 | R12: =IF(OR(P12>=40000, Q12="700"), "APPROVED", "No") -> No
C13: Rohan | D13: 90 | E13: No | I13: Rohan | J13: 4000 | K13: Yes | L13: =IF(OR(J13>=10000, K13="Yes"), "Yes", "No") -> Yes | O13: Vijay | P13: 50000 | Q13: 650 | R13: =IF(OR(P13>=40000, Q13="700"), "APPROVED", "No") -> APPROVED
C14: Deepa | D14: 80 | E14: Yes | I14: Divya | J14: 3000 | K14: No | L14: =IF(OR(J14>=10000, K14="Yes"), "Yes", "No") -> No | O14: Nisha | P14: 20000 | Q14: 600 | R14: =IF(OR(P14>=40000, Q14="700"), "APPROVED", "No") -> No
D18: Name | E18: Present | F18: Status | L18: Number 1 | M18: Number 2 | N18: Result | P18: Employee Name | Q18: Targets Achieved | R18: Attendance % | S18: Performance
D19: Aman | E19: TRUE | F19: =IF(NOT(E19="TRUE"),"ABSENT","PRESENT") -> ABSENT | L19: 10 | M19: 2 | N19: =IFERROR(L19/M19,"INVALID") -> 5 | P19: Raj | Q19: 45 | R19: 92 | S19: =IF(AND(R19>=90,Q19>=40),"EXCELLENT",IF(R19>=80,"GOOD","NEED IMPROVEMENT")) -> EXCELLENT
D20: Bharti | E20: FALSE | F20: =IF(NOT(E20="TRUE"),"ABSENT","PRESENT") -> ABSENT | L20: 15 | M20: 0 | N20: =IFERROR(L20/M20,"INVALID") -> INVALID | P20: Sunita | Q20: 38 | R20: 85 | S20: =IF(AND(R20>=90,Q20>=40),"EXCELLENT",IF(R20>=80,"GOOD","NEED IMPROVEMENT")) -> GOOD
D21: Rohan | E21: TRUE | F21: =IF(NOT(E21="TRUE"),"ABSENT","PRESENT") -> ABSENT | L21: 20 | M21: 5 | N21: =IFERROR(L21/M21,"INVALID") -> 4 | P21: Manoj | Q21: 50 | R21: 95 | S21: =IF(AND(R21>=90,Q21>=40),"EXCELLENT",IF(R21>=80,"GOOD","NEED IMPROVEMENT")) -> EXCELLENT
D22: Deepa | E22: FALSE | F22: =IF(NOT(E22="TRUE"),"ABSENT","PRESENT") -> ABSENT | L22: 8 | M22: 0 | N22: =IFERROR(L22/M22,"INVALID") -> INVALID | P22: Kavita | Q22: 30 | R22: 70 | S22: =IF(AND(R22>=90,Q22>=40),"EXCELLENT",IF(R22>=80,"GOOD","NEED IMPROVEMENT")) -> NEED IMPROVEMENT
P23: Task
P24: Attendance ≥ 90 AND Targets ≥ 40 → Excellent
P25: Attendance ≥ 80 → Good
P26: Else → Needs Improvement

Sheet Sheet6
A1: Vlookup
A3: emp id | B3: Name | C3: department | D3: salary | E3: city
A4: E101 | B4: AMIT | C4: HR | D4: 45000 | E4: Ahmedabad
A5: E102 | B5: NEHA | C5: IT | D5: 60000 | E5: Mumbai | I5: emp id | J5: name | L5: DEPARTMENT | M5: SALARY | O5: emp id | P5: city
A6: E103 | B6: RAHUL | C6: Finance | D6: 55000 | E6: Delhi | I6: E101 | J6: =IFERROR(VLOOKUP(I6,A3:E13,2,0),"INVALID") -> AMIT | L6: HR | O6: E101 | P6: =VLOOKUP(O6,A3:E13,5,0) -> Ahmedabad
A7: E104 | B7: PRIYA | C7: Sales | D7: 50000 | E7: Pune | I7: E102 | J7: =IFERROR(VLOOKUP(I7,A4:E14,2,0),"INVALID") -> NEHA | L7: HR | M7: =VLOOKUP(L7,C4:E14,2,0) -> 45000 | O7: E102 | P7: =VLOOKUP(O7,A4:E14,5,0) -> Mumbai
A8: E105 | B8: KARAN | C8: IT | D8: 65000 | E8: Bengaluru | I8: E103 | J8: =IFERROR(VLOOKUP(I8,A5:E15,2,0),"INVALID") -> RAHUL | L8: IT | M8: =VLOOKUP(L8,C5:E15,2,0) -> 60000 | O8: E103 | P8: =VLOOKUP(O8,A5:E15,5,0) -> Delhi
A9: E106 | B9: SNEHA | C9: HR | D9: 47000 | E9: Jaipur | I9: E104 | J9: =IFERROR(VLOOKUP(I9,A6:E16,2,0),"INVALID") -> PRIYA | L9: IT | M9: =VLOOKUP(L9,C6:E16,2,0) -> 65000 | O9: E104 | P9: =VLOOKUP(O9,A6:E16,5,0) -> Pune
A10: E107 | B10: ARJUN | C10: Marketing | D10: 58000 | E10: Hyderabad | I10: E105 | J10: =IFERROR(VLOOKUP(I10,A7:E17,2,0),"INVALID") -> KARAN | L10: IT | M10: =VLOOKUP(L10,C7:E17,2,0) -> 65000 | O10: E105 | P10: =VLOOKUP(O10,A7:E17,5,0) -> Bengaluru
A11: E108 | B11: MEERA | C11: Finance | D11: 62000 | E11: Chennai | I11: E106 | J11: =IFERROR(VLOOKUP(I11,A8:E18,2,0),"INVALID") -> SNEHA | L11: Finance | M11: =VLOOKUP(L11,C8:E18,2,0) -> 62000 | O11: E106 | P11: =VLOOKUP(O11,A8:E18,5,0) -> Jaipur
A12: E109 | B12: VIKRAM | C12: Sales | D12: 53000 | E12: Kolkata | I12: E107 | J12: =IFERROR(VLOOKUP(I12,A9:E19,2,0),"INVALID") -> ARJUN | L12: Finance | M12: =VLOOKUP(L12,C9:E19,2,0) -> 62000 | O12: E107 | P12: =VLOOKUP(O12,A9:E19,5,0) -> Hyderabad
A13: E110 | B13: RIYA | C13: IT | D13: 70000 | E13: Surat | I13: E108 | J13: =IFERROR(VLOOKUP(I13,A10:E20,2,0),"INVALID") -> MEERA | L13: Marketing | M13: =VLOOKUP(L13,C10:E20,2,0) -> 58000 | O13: E108 | P13: =VLOOKUP(O13,A10:E20,5,0) -> Chennai
I14: E109 | J14: =IFERROR(VLOOKUP(I14,A11:E21,2,0),"INVALID") -> VIKRAM | O14: E109 | P14: =VLOOKUP(O14,A11:E21,5,0) -> Kolkata
I15: E110 | J15: =IFERROR(VLOOKUP(I15,A12:E22,2,0),"INVALID") -> RIYA | O15: E110 | P15: =VLOOKUP(O15,A12:E22,5,0) -> Surat
A19: EMP ID | B19: DEPARTMENT | C19: SALARY | I19: EMP ID | J19: SALARY | M19: emp id | N19: E101 | O19: E102 | P19: E103 | Q19: E104 | R19: E105 | S19: E106 | T19: E107 | U19: E108 | V19: E109 | W19: E110
A20: E101 | B20: {=_xlfn.XLOOKUP(A20,A4:A13,C4:D13,"INVALID")} -> HR | C20: 45000 | I20: E106 | J20: =VLOOKUP($I$20,$A$2:$E$13,4,0) -> 47000 | M20: Name | N20: AMIT | O20: NEHA | P20: RAHUL | Q20: PRIYA | R20: KARAN | S20: SNEHA | T20: ARJUN | U20: MEERA | V20: VIKRAM | W20: RIYA
A21: E102 | B21: {=_xlfn.XLOOKUP(A21,A5:A14,C5:D14,"INVALID")} -> IT | C21: 60000 | M21: department | N21: HR | O21: IT | P21: Finance | Q21: Sales | R21: IT | S21: HR | T21: Marketing | U21: Finance | V21: Sales | W21: IT
A22: E103 | B22: {=_xlfn.XLOOKUP(A22,A6:A15,C6:D15,"INVALID")} -> Finance | C22: 55000 | M22: salary | N22: 45000 | O22: 60000 | P22: 55000 | Q22: 50000 | R22: 65000 | S22: 47000 | T22: 58000 | U22: 62000 | V22: 53000 | W22: 70000
A23: E104 | B23: {=_xlfn.XLOOKUP(A23,A7:A16,C7:D16,"INVALID")} -> Sales | C23: 50000 | M23: city | N23: Ahmedabad | O23: Mumbai | P23: Delhi | Q23: Pune | R23: Bengaluru | S23: Jaipur | T23: Hyderabad | U23: Chennai | V23: Kolkata | W23: Surat
A24: E105 | B24: {=_xlfn.XLOOKUP(A24,A8:A17,C8:D17,"INVALID")} -> IT | C24: 65000
A25: E106 | B25: {=_xlfn.XLOOKUP(A25,A9:A18,C9:D18,"INVALID")} -> HR | C25: 47000

Sheet Sheet7
A1: sheet 6 lookup,vlookup,xlookup practice
A3: Employee id | B3: Name | C3: Department | D3: Location | E3: Salary | F3: JoiningYear | H3: EMPLOYEE ID | I3: NAME | K3: EMPLOYEE ID | L3: DEPARTMENT | N3: NAME | O3: SALARY | Q3: EMP ID | R3: LOCATION | T3: EMP ID | U3: DEPARTMENT | W3: EMP ID | X3: JOINING YEAR
A4: E101 | B4: Rahul Sharma | C4: Sales | D4: Mumbai | E4: 45000 | F4: 2019 | H4: E101 | I4: =VLOOKUP(H4,A4:F11,2,0) -> Rahul Sharma | K4: E105 | L4: =VLOOKUP(K4,A4:F11,3,0) -> Marketing | N4: Neha Singh | O4: =VLOOKUP(N4,B4:F11,4,0) -> 58000 | Q4: E107 | R4: =VLOOKUP(Q4,A4:F11,4,0) -> Hyderabad | T4: E109 | U4: =IFERROR(VLOOKUP(T4,A4:C11,3,0),"INVALID") -> INVALID | W4: E103 | X4: =VLOOKUP(W4,A4:F11,6,0) -> 2020
A5: E102 | B5: Ananya Gupta | C5: HR | D5: Delhi | E5: 52000 | F5: 2018 | H5: E102 | I5: =VLOOKUP(H5,A5:F12,2,0) -> Ananya Gupta
A6: E103 | B6: Rohit Verma | C6: IT | D6: Bangalore | E6: 65000 | F6: 2020 | H6: E103 | I6: =VLOOKUP(H6,A6:F13,2,0) -> Rohit Verma
A7: E104 | B7: Neha Singh | C7: Finance | D7: Pune | E7: 58000 | F7: 2017 | H7: E104 | I7: =VLOOKUP(H7,A7:F14,2,0) -> Neha Singh
A8: E105 | B8: Aman Kumar | C8: Marketing | D8: Mumbai | E8: 48000 | F8: 2021 | H8: E105 | I8: =VLOOKUP(H8,A8:F15,2,0) -> Aman Kumar
A9: E106 | B9: Pooja Mehta | C9: IT | D9: Chennai | E9: 62000 | F9: 2019
A10: E107 | B10: Suresh Rao | C10: Sales | D10: Hyderabad | E10: 47000 | F10: 2020
A11: E108 | B11: Kavita Iyer | C11: HR | D11: Bangalore | E11: 54000 | F11: 2016
A15: EMP ID | B15: SALARY | D15: EMP ID | E15: DEPARTMENT | G15: NAME | H15: location | J15: emp id | K15: department | M15: DEPARTMENT | N15: BONUS
A16: E104 | B16: =_xlfn.XLOOKUP(A16,A4:A11,E4:E11,"INVALID") -> 58000 | D16: E101 | E16: =_xlfn.XLOOKUP(D16,A4:A11,C4:C11,"INVALID") -> Sales | G16: Suresh Rao | H16: =_xlfn.XLOOKUP(G16,B4:B11,D4:D11,"INVALID") -> Hyderabad | J16: E999 | K16: =_xlfn.XLOOKUP(J16,A4:A11,C4:C11,"employee not found") -> employee not found | M16: FINANCE | N16: =_xlfn.XLOOKUP(M16,A19:F19,A20:F20,"INVALID") -> 0.15
A19: Department | B19: Sales | C19: HR | D19: IT | E19: Finance | F19: Marketing | H19: DEPARTMENT | I19: BONUS | K19: EMP ID | L19: BONUS AMOUNT | N19: DEPARTMENT | O19: BONUS
A20: Bonus % | B20: 0.1 | C20: 0.08 | D20: 0.12 | E20: 0.15 | F20: 0.09 | H20: FINANCE | I20: =HLOOKUP(H20,A19:F20,2,0) -> 0.15 | K20: E107 | L20: =HLOOKUP($K$20,$A$31:$I$36,5,0)*HLOOKUP($K$20,$A$19:$F$20,2,0) -> #N/A | N20: CIVIL | O20: =IFERROR(HLOOKUP(N20,A19:F20,2,0),"INVALID") -> INVALID
H21: IT | I21: =HLOOKUP(H21,A19:F20,2,0) -> 0.12
K25: E101 | L25: =HLOOKUP(K25,A31:I36,5,0) * HLOOKUP(HLOOKUP(K25,A31:I36,3,0),A19:F20,2,0) -> 4500
K26: E102
K27: E103
K28: E104
A31: Employee id | B31: E101 | C31: E102 | D31: E103 | E31: E104 | F31: E105 | G31: E106 | H31: E107 | I31: E108
A32: Name | B32: Rahul Sharma | C32: Ananya Gupta | D32: Rohit Verma | E32: Neha Singh | F32: Aman Kumar | G32: Pooja Mehta | H32: Suresh Rao | I32: Kavita Iyer
A33: Department | B33: Sales | C33: HR | D33: IT | E33: Finance | F33: Marketing | G33: IT | H33: Sales | I33: HR
A34: Location | B34: Mumbai | C34: Delhi | D34: Bangalore | E34: Pune | F34: Mumbai | G34: Chennai | H34: Hyderabad | I34: Bangalore
A35: Salary | B35: 45000 | C35: 52000 | D35: 65000 | E35: 58000 | F35: 48000 | G35: 62000 | H35: 47000 | I35: 54000
A36: JoiningYear | B36: 2019 | C36: 2018 | D36: 2020 | E36: 2017 | F36: 2021 | G36: 2019 | H36: 2020 | I36: 2016

Sheet Sheet8
A1: Order ID | B1: Customer | C1: Product | D1: Qty | E1: Unit Price | F1: Status | G1: TOTAL AMOUNT
A2: O101 | B2: Amit | C2: Laptop | D2: 2 | E2: 45000 | F2: Delivered | G2: =PRODUCT(D2,E2) -> 90000
A3: O102 | B3: Neha | C3: Mouse | D3: 5 | E3: 700 | F3: Pending | G3: =PRODUCT(D3,E3) -> 3500
A4: O103 | B4: Ravi | C4: Keyboard | D4: 3 | E4: 1500 | F4: Delivered | G4: =PRODUCT(D4,E4) -> 4500
A5: O104 | B5: Priya | C5: Monitor | D5: 1 | E5: 18000 | F5: Cancelled | G5: =PRODUCT(D5,E5) -> 18000
