Workbook

Sheet Instructions
A1: MS Excel Practical Exam
A2: Total Questions: 30
A3: Difficulty Level: Medium
A4: Syllabus: Formulas, Logical Functions, Lookups, INDEX-MATCH, Pivot Tables & Charts, Data Analysis
A5: Attempt all questions using appropriate Excel tools/functions.

Sheet Sales_Data
A1: Order_ID | B1: Region | C1: Salesperson | D1: Product | E1: Quantity | F1: Unit_Price | G1: Sales_Date
A2: 301 | B2: North | C2: Amit | D2: Laptop | E2: 2 | F2: 45000 | G2: 05-01-2025 | H2: =TEXT(G2,"mmm") -> Jan
A3: 302 | B3: South | C3: Riya | D3: Mobile | E3: 5 | F3: 15000 | G3: 07-01-2025 | H3: =TEXT(G3,"mmm") -> Jan
A4: 303 | B4: East | C4: Kunal | D4: Tablet | E4: 3 | F4: 18000 | G4: 10-01-2025 | H4: =TEXT(G4,"mmm") -> Jan
A5: 304 | B5: West | C5: Neha | D5: Laptop | E5: 1 | F5: 45000 | G5: 12-01-2025 | H5: =TEXT(G5,"mmm") -> Jan
A6: 305 | B6: North | C6: Amit | D6: Mobile | E6: 4 | F6: 15000 | G6: 15-01-2025 | H6: =TEXT(G6,"mmm") -> Jan
A7: 306 | B7: South | C7: Riya | D7: Laptop | E7: 2 | F7: 45000 | G7: 18-01-2025 | H7: =TEXT(G7,"mmm") -> Jan

Sheet Product_Master
A1: Product | B1: Category | C1: GST_%
A2: Laptop | B2: Electronics | C2: 18
A3: Mobile | B3: Electronics | C3: 12
A4: Tablet | B4: Electronics | C4: 12

Sheet Student_Marks
A1: Student_ID | B1: Name | C1: Maths | D1: Statistics | E1: Excel | F1: Attendance_%
A2: 1 | B2: Rahul | C2: 78 | D2: 82 | E2: 85 | F2: 92
A3: 2 | B3: Sneha | C3: 88 | D3: 91 | E3: 90 | F3: 96
A4: 3 | B4: Arjun | C4: 65 | D4: 70 | E4: 72 | F4: 85
A5: 4 | B5: Pooja | C5: 92 | D5: 89 | E5: 94 | F5: 98
A6: 5 | B6: Vikas | C6: 55 | D6: 60 | E6: 58 | F6: 80

Sheet Questions
A1: 1. Calculate Total Sales for each order (Quantity × Unit_Price). | J1: 2
A2: 2. Calculate GST Amount using VLOOKUP from Product_Master. | J2: 2
A3: 3. Find Final Amount payable (Total Sales + GST). | J3: 2
A4: 4. Find Grand Total of Final Amount. | J4: 2
A5: 5. Count total number of orders using COUNTA. | J5: 2
A6: 6. Find Region-wise total sales using SUMIF. | J6: 2
A7: 7. Use IF to classify Quantity as High (>3) or Low (<=3). | J7: 2
A8: 8. Find the maximum and minimum Final Amount. | J8: 2
A9: 9. Extract month name from Sales_Date. | J9: 2
A10: 10. Sort Sales_Data by Final Amount (Descending). | J10: 2
A11: 11. Use INDEX-MATCH to fetch Product Category. | J11: 2
A12: 12. Calculate average marks of each student. | J12: 2
... A30: 30. Protect the Student_Marks sheet. | J30: 2
J32: =SUM(J1:J30) -> 60

Sheet answers
A1: Order_ID | B1: Region | C1: 2 st name | D1: Salesperson | E1: Product | F1: Category | G1: Quantity | H1: unit price | J1: Sales_Date | K1: Total sales | L1: GST AMOUNT | M1: FINAL AMOUNT | N1: MAX/MIN AMOUNT | O1: MONTH | P1: LOW OR HIGH | Q1: REGION | R1: SALES AMOUNT
A2: 301 | B2: North | C2: =LEFT(D2,2) -> Am | D2: Amit | E2: Laptop | F2: =INDEX(Product_Master!B2:B4,MATCH(Sales_Data!D2,Product_Master!A2:A4,0)) -> Electronics | G2: 2 | H2: 45000 | I2: =ROUND(H2,1000) -> 45000 | J2: 05-01-2025 | K2: =PRODUCT(G2,H2) -> 90000 | L2: =K2*VLOOKUP(answers!E2,Product_Master!A1:C4,3,FALSE)/100 -> 16200 | M2: =SUM(K2,L2) -> 106200 | N2: =IF(M2>85000,"MAX","MIN") -> MAX | O2: =TEXT(J2,"MMMM") -> January | P2: =IF(G2>3,"HIGH","LOW") -> LOW | Q2: NORTH | R2: =SUMIF(B2:B7,Q2,K2:K7) -> 90000
A3: 302 | B3: South | C3: =LEFT(D3,2) -> Ri | D3: Riya | E3: Mobile | F3: =INDEX(Product_Master!B3:B5,MATCH(Sales_Data!D3,Product_Master!A3:A5,0)) -> Electronics | G3: 5 | H3: 15000 | I3: =ROUND(H3,1000) -> 15000 | J3: 07-01-2025 | K3: =PRODUCT(G3,H3) -> 75000 | L3: =K3*VLOOKUP(answers!E3,Product_Master!A2:C5,3,FALSE)/100 -> 9000 | M3: =SUM(K3,L3) -> 84000 | N3: =IF(M3>85000,"MAX","MIN") -> MIN | O3: =TEXT(J3,"MMMM") -> January | P3: =IF(G3>3,"HIGH","LOW") -> HIGH | Q3: SOUTH | R3: =SUMIF(B3:B8,Q3,K3:K8) -> 75000
A4: 303 | B4: East | C4: =LEFT(D4,2) -> Ku | D4: Kunal | E4: Tablet | F4: =INDEX(Product_Master!$B$4:$B$6,MATCH(Sales_Data!$D$4,Product_Master!$A$4:$A$6,0)) -> Electronics | G4: 3 | H4: 18000 | I4: =ROUND(H4,1000) -> 18000 | J4: 10-01-2025 | K4: =PRODUCT(G4,H4) -> 54000 | L4: =K4*VLOOKUP(answers!E4,Product_Master!A3:C6,3,FALSE)/100 -> 6480 | M4: =SUM(K4,L4) -> 60480 | N4: =IF(M4>85000,"MAX","MIN") -> MIN | O4: =TEXT(J4,"MMMM") -> January | P4: =IF(G4>3,"HIGH","LOW") -> LOW | Q4: WEST | R4: =SUMIF(B4:B9,Q4,K4:K9) -> 45000
A5: 304 | B5: West | C5: =LEFT(D5,2) -> Ne | D5: Neha | E5: Laptop | F5: =INDEX(Product_Master!$B$4:$B$6,MATCH(Sales_Data!$D$4,Product_Master!$A$4:$A$6,0)) -> Electronics | G5: 1 | H5: 45000 | I5: =ROUND(H5,1000) -> 45000 | J5: 12-01-2025 | K5: =PRODUCT(G5,H5) -> 45000 | L5: =K5*VLOOKUP(E5,Product_Master!A1:C4,3,FALSE)/100 -> 8100 | M5: =SUM(K5,L5) -> 53100 | N5: =IF(M5>85000,"MAX","MIN") -> MIN | O5: =TEXT(J5,"MMMM") -> January | P5: =IF(G5>3,"HIGH","LOW") -> LOW | Q5: EAST | R5: =SUMIF(B5:B10,Q5,K5:K10) -> 0
N6: =IF(M6>85000,"MAX","MIN") -> MIN | O6: =TEXT(J6,"MMMM") -> January | P6: =IF(G6>3,"HIGH","LOW") -> LOW
N7: =IF(M7>85000,"MAX","MIN") -> MIN | O7: =TEXT(J7,"MMMM") -> January | P7: =IF(G7>3,"HIGH","LOW") -> LOW
A8: =COUNTA(A2:A7) -> 4 | E8: =COUNTIFS(answers!E2:E7,"laptop",answers!B2:B7,"north") -> 1 | M8: =SUM(M2:M7) -> 303780 | N8: (GRAND TOTAL)
A9: (TOTAL ORDER) | M9: =MAX(M2:M7) -> 106200 | N9: (MAX AMOUNT)
M10: =MIN(M2:M7) -> 53100 | N10: (MIN AMOUNT)
H13: Name | J13: Excel
H14: Rahul | J14: 85
H15: Sneha | J15: 90
H16: Arjun | J16: 72
H17: Pooja | J17: 94
H18: Vikas | J18: 58
D20: Student_ID | E20: Name | F20: Maths | G20: Statistics | H20: Excel | J20: Attendance_% | K20: average | L20: topper name | M20: Eligiblity | N20: median | O20: student id and name
D21: 1 | E21: Rahul | F21: 78 | G21: 82 | H21: 85 | J21: 92 | K21: =AVERAGE(F21,G21,H21) -> 81.666667 | L21: =INDEX(answers!E21:E25,MATCH(MAX(answers!K21:K25),answers!K21:K25,0)) -> Pooja | M21: {=IF(J21:J25>=85,"eligible","not eligible")} -> eligible | N21: =MEDIAN($G$21:$G$25) -> 82 | O21: =_xlfn.CONCAT(D21,E21) -> 1Rahul
D22: 2 | E22: Sneha | F22: 88 | G22: 91 | H22: 90 | J22: 96 | K22: =AVERAGE(F22,G22,H22) -> 89.666667 | M22: eligible | N22: =MEDIAN($G$21:$G$25) -> 82 | O22: =_xlfn.CONCAT(D22,E22) -> 2Sneha
D23: 3 | E23: Arjun | F23: 65 | G23: 70 | H23: 72 | J23: 85 | K23: =AVERAGE(F23,G23,H23) -> 69 | M23: eligible | N23: =MEDIAN($G$21:$G$25) -> 82 | O23: =_xlfn.CONCAT(D23,E23) -> 3Arjun
D24: 4 | E24: Pooja | F24: 92 | G24: 89 | H24: 94 | J24: 98 | K24: =AVERAGE(F24,G24,H24) -> 91.666667 | M24: eligible | N24: =MEDIAN($G$21:$G$25) -> 82 | O24: =_xlfn.CONCAT(D24,E24) -> 4Pooja
D25: 5 | E25: Vikas | F25: 55 | G25: 60 | H25: 58 | J25: 80 | K25: =AVERAGE(F25,G25,H25) -> 57.666667 | M25: not eligible | N25: =MEDIAN($G$21:$G$25) -> 82 | O25: =_xlfn.CONCAT(D25,E25) -> 5Vikas
H26: =_xlfn.STDEV.S(H21:H25) -> 14.737707 | J26: =COUNTIF(J21:J25,">90") -> 3 | K26: =MAX(K21:K25) -> 91.666667
H27: (std deviation) | J27: (attendence>90)

Sheet Sheet4
A3: Row Labels | B3: Sum of FINAL AMOUNT
A4: Laptop | B4: 265500
A5: Mobile | B5: 151200
A6: Tablet | B6: 60480
A7: Grand Total | B7: 477180
H9: Row Labels | I9: Sum of FINAL AMOUNT
H10: East | I10: 60480
H11: North | I11: 173400
H12: South | I12: 190200
H13: West | I13: 53100
H14: Grand Total | I14: 477180
A24: Row Labels | B24: Sum of FINAL AMOUNT
A25: Laptop | B25: 265500
A26: Mobile | B26: 151200
A27: Tablet | B27: 60480
A28: Grand Total | B28: 477180
